isogeo_pysdk/__about__.py
isogeo_pysdk/__init__.py
isogeo_pysdk/api_hooks.py
isogeo_pysdk/checker.py
isogeo_pysdk/decorators.py
isogeo_pysdk/exceptions.py
isogeo_pysdk/isogeo.py
isogeo_pysdk/translator.py
isogeo_pysdk/type_hints_custom.py
isogeo_pysdk/utils.py
isogeo_pysdk/api/__init__.py
isogeo_pysdk/api/routes_about.py
isogeo_pysdk/api/routes_account.py
isogeo_pysdk/api/routes_application.py
isogeo_pysdk/api/routes_catalog.py
isogeo_pysdk/api/routes_condition.py
isogeo_pysdk/api/routes_conformity.py
isogeo_pysdk/api/routes_contact.py
isogeo_pysdk/api/routes_coordinate_systems.py
isogeo_pysdk/api/routes_datasource.py
isogeo_pysdk/api/routes_directives.py
isogeo_pysdk/api/routes_event.py
isogeo_pysdk/api/routes_feature_attributes.py
isogeo_pysdk/api/routes_format.py
isogeo_pysdk/api/routes_invitation.py
isogeo_pysdk/api/routes_keyword.py
isogeo_pysdk/api/routes_license.py
isogeo_pysdk/api/routes_limitation.py
isogeo_pysdk/api/routes_link.py
isogeo_pysdk/api/routes_metadata.py
isogeo_pysdk/api/routes_metadata_bulk.py
isogeo_pysdk/api/routes_search.py
isogeo_pysdk/api/routes_service.py
isogeo_pysdk/api/routes_service_layers.py
isogeo_pysdk/api/routes_service_operations.py
isogeo_pysdk/api/routes_share.py
isogeo_pysdk/api/routes_specification.py
isogeo_pysdk/api/routes_thesaurus.py
isogeo_pysdk/api/routes_user.py
isogeo_pysdk/api/routes_workgroup.py
isogeo_pysdk/enums/__init__.py
isogeo_pysdk/enums/application_types.py
isogeo_pysdk/enums/bulk_actions.py
isogeo_pysdk/enums/bulk_ignore_reasons.py
isogeo_pysdk/enums/bulk_targets.py
isogeo_pysdk/enums/catalog_statistics_tags.py
isogeo_pysdk/enums/contact_roles.py
isogeo_pysdk/enums/contact_types.py
isogeo_pysdk/enums/edition_profiles.py
isogeo_pysdk/enums/event_kinds.py
isogeo_pysdk/enums/keyword_casing.py
isogeo_pysdk/enums/limitation_restrictions.py
isogeo_pysdk/enums/limitation_types.py
isogeo_pysdk/enums/link_actions.py
isogeo_pysdk/enums/link_kinds.py
isogeo_pysdk/enums/link_types.py
isogeo_pysdk-3.10.0.dist-info/licenses/LICENSE
isogeo_pysdk-3.10.0.dist-info/METADATA
isogeo_pysdk-3.10.0.dist-info/WHEEL
isogeo_pysdk-3.10.0.dist-info/top_level.txt
isogeo_pysdk-3.10.0.dist-info/RECORD
