Metadata-Version: 2.4
Name: isogeo-pysdk
Version: 3.10.0
Summary: Python SDK for Isogeo API
Author-email: Isogeo <contact@isogeo.com>
License-Expression: LGPL-3.0-or-later
Project-URL: Docs, https://isogeo-api-pysdk.readthedocs.io/
Project-URL: BugReports, https://github.com/isogeo/isogeo-api-py-minsdk/issues/
Project-URL: Source, https://github.com/isogeo/isogeo-api-py-minsdk/
Project-URL: Isogeo API, http://help.isogeo.com/api/
Keywords: GIS,metadata,INSPIRE,Isogeo,API,REST,geographical data,ISO19139
Classifier: Intended Audience :: Developers
Classifier: Intended Audience :: Information Technology
Classifier: Programming Language :: Python :: 3
Classifier: Programming Language :: Python :: 3.9
Classifier: Programming Language :: Python :: 3.10
Classifier: Programming Language :: Python :: 3.11
Classifier: Development Status :: 5 - Production/Stable
Classifier: Operating System :: OS Independent
Classifier: Topic :: Software Development :: Libraries :: Python Modules
Requires-Python: <4,>=3.9
License-File: LICENSE
Requires-Dist: requests>=2.20.0
Requires-Dist: requests-oauthlib>=1.2.0
Provides-Extra: dev
Requires-Dist: black; extra == "dev"
Requires-Dist: python-dotenv; extra == "dev"
Provides-Extra: test
Requires-Dist: pytest; extra == "test"
Requires-Dist: pytest-cov; extra == "test"
Dynamic: license-file
